lzhbrowser/__init__.py
lzhbrowser-0.1.3.dist-info/METADATA
lzhbrowser-0.1.3.dist-info/WHEEL
lzhbrowser-0.1.3.dist-info/top_level.txt
lzhbrowser-0.1.3.dist-info/RECORD
