Metadata-Version: 2.4
Name: lzhbrowser
Version: 0.1.3
Summary: 一个`playwright`实例，支持`cookie`、自动代理(白名单)、远程调试、设定加载内容
Author-email: lzh <zhhtdm@hotmail.com>
License: MIT
Project-URL: Homepage, https://github.com/zhhtdm/pypi-browser
Project-URL: Repository, https://github.com/zhhtdm/pypi-browser
Requires-Python: >=3.9
Requires-Dist: playwright
Requires-Dist: lzhgetlogger
